design/uart/uart_tx.sv
module uart_tx #(
    DBIT = 8,
    SB_TICK = 16
) (
    input logic clk,
    reset,
    input logic tx_start,
    input logic [7:0] d_tx,
    output logic tx_done_tick,
    output logic tx
);

  typedef enum {
    idle,
    load,
    data,
    stop
  } state_type;

  state_type state_current, state_next;
  logic [4:0] bit_count;
  logic [7:0] shift_reg;
  logic tx_reg, tx_next;

  always_ff @(posedge clk, posedge reset)
    if (reset) begin
      state_current <= idle;
    end else begin
      state_current <= state_next;
    end
    
    
  always_ff @(posedge clk, posedge reset)
    if (reset) begin
      bit_count <= 0;
    end 
    else if(!(state_current==data)) begin
      bit_count <= 0;
    end
    else begin
      bit_count <= bit_count + 1;
    end
  


  always_comb begin
    
    case (state_current)
      idle: begin
        tx_reg = 1;
        if(tx_start==1)
          state_next = load;
      end 

      load: begin
        tx_reg = 0;
        if(bit_count==0)begin
          shift_reg = d_tx;
          state_next = data;
        end
        else
          state_next = load;
      end

      data: begin
        tx_reg = shift_reg[bit_count];
          if(bit_count>=DBIT-1)
            state_next = stop;
          else 
            state_next = data;
      end

      stop: begin
        tx_reg = 1;
          if(tx_start==0)
            state_next = idle;
          else
            state_next = stop;
      end
    endcase

  end

  assign tx = tx_reg;

endmodule

design/uart/uart_reg.sv
module uart_reg (
    input logic        clk,
    input logic        write_enable,
    input logic [ 4:0] address,
    input logic [30:0] data_in,
    input logic        tx_done,
    input logic        snum,
    input logic        rx_done,
    input logic [7:0]  d_rx,
    input logic        rxing,

    output logic [10:0] dvsr,
    output logic [7:0] data_out,
    output logic tx_start,
    output logic full,
    output logic [31:0] cout,
    output logic tx_int,
    output logic rx_int
);

  logic [31:0] registers[0:5];
  

  always @(negedge clk) begin
    if (write_enable) begin
      if((address>>2)==0)
      registers[address>>2] <= {1'b1,data_in};
      else
      registers[address>>2] <= data_in;
    end
    else if (tx_done) begin
      registers[0] <= registers[0] & !(32'h80000000);
      registers[4][0] <= 1'b1;
    end
    else if (rxing) begin
      registers[3] <= registers[3] & !(32'h80000000);
    end
    else if (rx_done) begin
      registers[3] <= d_rx;
      registers[4][1] <= 1'b1;
    end
    
  end

  assign data_out = registers[0][7:0];
  assign dvsr = registers[1][10:0];
  assign tx_start = registers[2][0];
  assign full = registers[0][31];
  assign snum = registers[2][1];
  assign tx_int = registers[5][0] & registers[4][0];
  assign rx_int = registers[5][1] & registers[4][1];

  always_comb begin
    if (address==5'b0 | address==5'hC) begin
      cout = 32'h80000000 & registers[address>>2];
    end
    else begin
      cout = registers[address>>2];
    end

  end


endmodule

design/uart/uart_baud.sv
module baud_gen (
    input logic clk,
    reset,
    input logic [10:0] dvsr,
    output logic tick
);

  logic [11:0] r_reg;
  logic [11:0] dvsr2;

  assign dvsr2 = dvsr<<1;


  always_ff @(clk, posedge reset)
    if (reset) begin
         r_reg <= 0;
         tick<=0;
    end
    else if(r_reg>=dvsr2-1) begin
        tick <= !tick;
        r_reg <= 0;
    end
    else 
        r_reg<= r_reg+1;


endmodule

design/uart/uart_top.sv
module uart_top (
    input  logic        clk,
    input  logic        reset,
    input  logic [31:0] cpu_address,
    input  logic [31:0] cpu_data,
    input  logic        write_enable
    // output logic [ 7:0] dout
);

  logic [10:0] dvsr;
  logic [ 7:0] data_out;
  logic tx_start;

  logic tick;


  baud_gen uart_baud_gen (
      .clk  (clk),
      .reset(reset),
      .dvsr (dvsr),
      .tick (tick)
  );

  uart_reg uart_reg_block (
      .clk(clk),
      .write_enable(write_enable),
      .address(cpu_address[4:0]),
      .data_in(cpu_data),

      .dvsr(dvsr),
      .data_out(data_out),
      .tx_start(tx_start)
  );

  //   uart_rx #(
  //       .DBIT(8),
  //       .SB_TICK(16)
  //   ) uart_receiver (
  //       .clk(clk),
  //       .reset(reset),
  //       .rx(rx),
  //       .s_tick(tick),
  //       .rx_done_tick(rx_done_tick),
  //       .dout(rx_data)
  //   );

  uart_tx #(
      .DBIT(8),
      .SB_TICK(16)
  ) uart_transmitter (
      .clk         (tick),
      .reset       (reset),
      .tx_start    (tx_start),
      .d_tx        (data_out),
      .tx_done_tick(tx_done_tick),
      .tx          (tx)
  );

endmodule

tb_uart_top.sv
`timescale 1ns / 1ps

module tb_uart_top;

  // Inputs to the UART top module
  logic clk;
  logic reset;
  logic [31:0] cpu_address;
  logic [31:0] cpu_data;
  logic write_enable;
  logic cpu_tx_start;

  // Outputs from the UART top module
  logic [7:0] dout;

  // Instantiate the uart_top module
  uart_top UUT (
      .clk(clk),
      .reset(reset),
      .cpu_address(cpu_address),
      .cpu_data(cpu_data),
      .write_enable(write_enable)
  );

  // Clock generation
  always #10 clk = ~clk;  // 50 MHz clock

  // Test scenarios
  initial begin
    // Initialize Inputs
    clk = 0;
    reset = 1;
    cpu_address = 0;
    cpu_data = 0;
    cpu_tx_start = 0;

    // Reset the system
    #25;  // Wait a bit
    reset = 1;
    #20;
    reset = 0;
    #20;

// Set the Data to be transferred
    write_enable = 1'b1;
    cpu_address = 32'h80000000;
    cpu_data    = 32'b01101001;
    #20;

// Set the Baudivisor according to (sys_clk/baudrate)-1  
    write_enable = 1'b1;
    cpu_address = 32'h80000004;
    cpu_data    = 8'h1; 
    #20;

// Inititate the transmission
    write_enable = 1'b1;
    cpu_address = 32'h80000008;
    cpu_data    = 8'h1; 
    #20;

    #500;

    $finish;
  end

  // Monitor changes
  initial begin
    $dumpfile("uart.vcd");
    $dumpvars(0, tb_uart_top);
  end

endmodule

uart.vcd
$date
	Sun Apr 14 06:00:00 2024
$end
$version
	ModelSim Version 2020.1
$end
$timescale
	1ps
$end

$scope module tb_uart_top $end
$var reg 1 ! clk $end
$var reg 1 " reset $end
$var reg 32 # cpu_address [31:0] $end
$var reg 32 $ cpu_data [31:0] $end
$var reg 1 % write_enable $end
$var reg 1 & cpu_tx_start $end
$var reg 8 ' dout [7:0] $end

$scope module UUT $end
$var wire 1 ( clk $end
$var wire 1 ) reset $end
$var wire 1 * cpu_address [31] $end
$var wire 1 + cpu_address [30] $end
$var wire 1 , cpu_address [29] $end
$var wire 1 - cpu_address [28] $end
$var wire 1 . cpu_address [27] $end
$var wire 1 / cpu_address [26] $end
$var wire 1 0 cpu_address [25] $end
$var wire 1 1 cpu_address [24] $end
$var wire 1 2 cpu_address [23] $end
$var wire 1 3 cpu_address [22] $end
$var wire 1 4 cpu_address [21] $end
$var wire 1 5 cpu_address [20] $end
$var wire 1 6 cpu_address [19] $end
$var wire 1 7 cpu_address [18] $end
$var wire 1 8 cpu_address [17] $end
$var wire 1 9 cpu_address [16] $end
$var wire 1 : cpu_address [15] $end
$var wire 1 ; cpu_address [14] $end
$var wire 1 < cpu_address [13] $end
$var wire 1 = cpu_address [12] $end
$var wire 1 > cpu_address [11] $end
$var wire 1 ? cpu_address [10] $end
$var wire 1 @ cpu_address [9] $end
$var wire 1 A cpu_address [8] $end
$var wire 1 B cpu_address [7] $end
$var wire 1 C cpu_address [6] $end
$var wire 1 D cpu_address [5] $end
$var wire 1 E cpu_address [4] $end
$var wire 1 F cpu_address [3] $end
$var wire 1 G cpu_address [2] $end
$var wire 1 H cpu_address [1] $end
$var wire 1 I cpu_address [0] $end
$var wire 1 J cpu_data [31] $end
$var wire 1 K cpu_data [30] $end
$var wire 1 L cpu_data [29] $end
$var wire 1 M cpu_data [28] $end
$var wire 1 N cpu_data [27] $end
$var wire 1 O cpu_data [26] $end
$var wire 1 P cpu_data [25] $end
$var wire 1 Q cpu_data [24] $end
$var wire 1 R cpu_data [23] $end
$var wire 1 S cpu_data [22] $end
$var wire 1 T cpu_data [21] $end
$var wire 1 U cpu_data [20] $end
$var wire 1 V cpu_data [19] $end
$var wire 1 W cpu_data [18] $end
$var wire 1 X cpu_data [17] $end
$var wire 1 Y cpu_data [16] $end
$var wire 1 Z cpu_data [15] $end
$var wire 1 [ cpu_data [14] $end
$var wire 1 \ cpu_data [13] $end
$var wire 1 ] cpu_data [12] $end
$var wire 1 ^ cpu_data [11] $end
$var wire 1 _ cpu_data [10] $end
$var wire 1 ` cpu_data [9] $end
$var wire 1 a cpu_data [8] $end
$var wire 1 b cpu_data [7] $end
$var wire 1 c cpu_data [6] $end
$var wire 1 d cpu_data [5] $end
$var wire 1 e cpu_data [4] $end
$var wire 1 f cpu_data [3] $end
$var wire 1 g cpu_data [2] $end
$var wire 1 h cpu_data [1] $end
$var wire 1 i cpu_data [0] $end
$var wire 1 j write_enable $end
$var reg 11 k dvsr [10:0] $end
$var reg 8 l data_out [7:0] $end
$var reg 1 m tx_start $end
$var reg 1 n tick $end
$var wire 1 o tx_done_tick $end
$var wire 1 p tx $end

$scope module uart_baud_gen $end
$var wire 1 ( clk $end
$var wire 1 ) reset $end
$var wire 1 q dvsr [10] $end
$var wire 1 r dvsr [9] $end
$var wire 1 s dvsr [8] $end
$var wire 1 t dvsr [7] $end
$var wire 1 u dvsr [6] $end
$var wire 1 v dvsr [5] $end
$var wire 1 w dvsr [4] $end
$var wire 1 x dvsr [3] $end
$var wire 1 y dvsr [2] $end
$var wire 1 z dvsr [1] $end
$var wire 1 { dvsr [0] $end
$var reg 1 | tick $end
$var reg 12 } r_reg [11:0] $end
$var reg 12 ~ dvsr2 [11:0] $end
$upscope $end

$scope module uart_reg_block $end
$var wire 1 ( clk $end
$var wire 1 j write_enable $end
$var wire 1 E address [4] $end
$var wire 1 F address [3] $end
$var wire 1 G address [2] $end
$var wire 1 H address [1] $end
$var wire 1 I address [0] $end
$var wire 1 J data_in [31] $end
$var wire 1 K data_in [30] $end
$var wire 1 L data_in [29] $end
$var wire 1 M data_in [28] $end
$var wire 1 N data_in [27] $end
$var wire 1 O data_in [26] $end
$var wire 1 P data_in [25] $end
$var wire 1 Q data_in [24] $end
$var wire 1 R data_in [23] $end
$var wire 1 S data_in [22] $end
$var wire 1 T data_in [21] $end
$var wire 1 U data_in [20] $end
$var wire 1 V data_in [19] $end
$var wire 1 W data_in [18] $end
$var wire 1 X data_in [17] $end
$var wire 1 Y data_in [16] $end
$var wire 1 Z data_in [15] $end
$var wire 1 [ data_in [14] $end
$var wire 1 \ data_in [13] $end
$var wire 1 ] data_in [12] $end
$var wire 1 ^ data_in [11] $end
$var wire 1 _ data_in [10] $end
$var wire 1 ` data_in [9] $end
$var wire 1 a data_in [8] $end
$var wire 1 b data_in [7] $end
$var wire 1 c data_in [6] $end
$var wire 1 d data_in [5] $end
$var wire 1 e data_in [4] $end
$var wire 1 f data_in [3] $end
$var wire 1 g data_in [2] $end
$var wire 1 h data_in [1] $end
$var wire 1 i data_in [0] $end
$var reg 11 !! dvsr [10:0] $end
$var reg 8 "! data_out [7:0] $end
$var reg 1 #! tx_start $end
$upscope $end

$scope module uart_transmitter $end
$var parameter 32 $! DBIT $end
$var parameter 32 %! SB_TICK $end
$var wire 1 &! clk $end
$var wire 1 ) reset $end
$var wire 1 '! tx_start $end
$var wire 1 (! d_tx [7] $end
$var wire 1 )! d_tx [6] $end
$var wire 1 *! d_tx [5] $end
$var wire 1 +! d_tx [4] $end
$var wire 1 ,! d_tx [3] $end
$var wire 1 -! d_tx [2] $end
$var wire 1 .! d_tx [1] $end
$var wire 1 /! d_tx [0] $end
$var reg 1 0! tx_done_tick $end
$var reg 1 1! tx $end
$var integer 32 2! state_current $end
$var integer 32 3! state_next $end
$var reg 5 4! bit_count [4:0] $end
$var reg 8 5! shift_reg [7:0] $end
$var reg 1 6! tx_reg $end
$var reg 1 7! tx_next $end
$upscope $end
$upscope $end
$upscope $end
$enddefinitions $end
#0
$dumpvars
0!
1"
b0 #
b0 $
x%
0&
bx '
bx k
bx l
xm
0n
0|
b0 }
bx0 ~
bx !!
bx "!
x#!
x0!
11!
b0 4!
bx 5!
16!
x7!
b1000 $!
b10000 %!
b0 2!
b0 3!
xo
1p
0(
1)
0I
0H
0G
0F
0E
0D
0C
0B
0A
0@
0?
0>
0=
0<
0;
0:
09
08
07
06
05
04
03
02
01
00
0/
0.
0-
0,
0+
0*
0i
0h
0g
0f
0e
0d
0c
0b
0a
0`
0_
0^
0]
0\
0[
0Z
0Y
0X
0W
0V
0U
0T
0S
0R
0Q
0P
0O
0N
0M
0L
0K
0J
xj
x{
xz
xy
xx
xw
xv
xu
xt
xs
xr
xq
0&!
x'!
x/!
x.!
x-!
x,!
x+!
x*!
x)!
x(!
$end
#10000
1!
1(
#20000
0!
0(
#30000
1!
1(
#40000
0!
0(
#45000
0"
0)
#50000
1!
1(
b1 }
#60000
0!
0(
b10 }
#65000
1%
b10000000000000000000000000000000 #
b1101001 $
1j
1i
1f
1d
1c
1*
#70000
1!
1(
b11 }
#80000
0!
0(
b100 }
b1101001 "!
b1101001 l
1/!
0.!
0-!
1,!
0+!
1*!
1)!
0(!
#85000
b10000000000000000000000000000100 #
b1 $
0f
0d
0c
1G
#90000
1!
1(
b101 }
#100000
0!
0(
b110 }
b1 !!
b1 k
1{
0z
0y
0x
0w
0v
0u
0t
0s
0r
0q
b10 ~
#105000
b10000000000000000000000000001000 #
0G
1F
#110000
1!
1(
1|
b0 }
1n
1&!
#120000
0!
0(
b1 }
1#!
1m
1'!
b1 3!
#130000
1!
1(
0|
b0 }
0n
0&!
#140000
0!
0(
b1 }
#150000
1!
1(
1|
b0 }
1n
1&!
b1 2!
06!
b1101001 5!
b10 3!
01!
0p
#160000
0!
0(
b1 }
#170000
1!
1(
0|
b0 }
0n
0&!
#180000
0!
0(
b1 }
#190000
1!
1(
1|
b0 }
1n
1&!
b10 2!
16!
11!
1p
#200000
0!
0(
b1 }
#210000
1!
1(
0|
b0 }
0n
0&!
#220000
0!
0(
b1 }
#230000
1!
1(
1|
b0 }
1n
1&!
b1 4!
06!
01!
0p
#240000
0!
0(
b1 }
#250000
1!
1(
0|
b0 }
0n
0&!
#260000
0!
0(
b1 }
#270000
1!
1(
1|
b0 }
1n
1&!
b10 4!
#280000
0!
0(
b1 }
#290000
1!
1(
0|
b0 }
0n
0&!
#300000
0!
0(
b1 }
#310000
1!
1(
1|
b0 }
1n
1&!
b11 4!
16!
11!
1p
#320000
0!
0(
b1 }
#330000
1!
1(
0|
b0 }
0n
0&!
#340000
0!
0(
b1 }
#350000
1!
1(
1|
b0 }
1n
1&!
b100 4!
06!
01!
0p
#360000
0!
0(
b1 }
#370000
1!
1(
0|
b0 }
0n
0&!
#380000
0!
0(
b1 }
#390000
1!
1(
1|
b0 }
1n
1&!
b101 4!
16!
11!
1p
#400000
0!
0(
b1 }
#410000
1!
1(
0|
b0 }
0n
0&!
#420000
0!
0(
b1 }
#430000
1!
1(
1|
b0 }
1n
1&!
b110 4!
#440000
0!
0(
b1 }
#450000
1!
1(
0|
b0 }
0n
0&!
#460000
0!
0(
b1 }
#470000
1!
1(
1|
b0 }
1n
1&!
b111 4!
06!
b11 3!
01!
0p
#480000
0!
0(
b1 }
#490000
1!
1(
0|
b0 }
0n
0&!
#500000
0!
0(
b1 }
#510000
1!
1(
1|
b0 }
1n
1&!
b11 2!
b1000 4!
16!
11!
1p
#520000
0!
0(
b1 }
#530000
1!
1(
0|
b0 }
0n
0&!
#540000
0!
0(
b1 }
#550000
1!
1(
1|
b0 }
1n
1&!
b0 4!
#560000
0!
0(
b1 }
#570000
1!
1(
0|
b0 }
0n
0&!
#580000
0!
0(
b1 }
#590000
1!
1(
1|
b0 }
1n
1&!
#600000
0!
0(
b1 }
#610000
1!
1(
0|
b0 }
0n
0&!
#620000
0!
0(
b1 }
